golang/__init__.py
golang/__version__.py
golang-0.0.3.dist-info/METADATA
golang-0.0.3.dist-info/WHEEL
golang-0.0.3.dist-info/top_level.txt
golang-0.0.3.dist-info/RECORD
